{
  "accept_predicate_comparison_sites": 3,
  "accept_predicate_expected_depth": 1.8118525468120872,
  "accept_predicate_num_intervals": 2,
  "accept_predicate_worst_case_depth": 3,
  "avg_semantic_comparisons_per_emitted_token": 7.162323723347932,
  "avg_semantic_comparisons_per_visited_state": 2.2622483292895756,
  "benchmark_family": "Small C-like lexer",
  "benchmark_id": "BM1",
  "binary_size_bytes": 29416,
  "branch_misses": null,
  "branch_sites": 16,
  "branches": null,
  "bytes_per_second_aggregate": 175660231.53966853,
  "classifier_instruction_count": 5,
  "classifier_kind": "linear_threshold_chain",
  "classifier_max_intervals_per_class": 1,
  "classifier_ns_per_call": 0.5103682689281437,
  "classifier_source_bytes": 2183,
  "classifier_total_intervals": 17,
  "classifier_trace_ns_total": 20312209,
  "classify_calls_total": 328902,
  "compare_sites": 16,
  "comparison_sites": 16,
  "comparisons_per_state_visit": 2.2645127242875573,
  "compile_failed": false,
  "compiled_instruction_count": 5,
  "compiler": "gcc",
  "compiler_id": "gcc_O3",
  "completed": true,
  "cycles": null,
  "default_semantic_max_intervals_per_class": 1,
  "default_semantic_total_intervals_in_layout": 17,
  "emitted_tokens_total": 103885,
  "error_message": "",
  "estimated_classification_share_of_full_scan": 0.1310401676726628,
  "estimated_transition_share_of_full_scan": 0.1707092994023227,
  "eval_group": "B",
  "eval_source": "B",
  "expected_depth": 2.2645127242875573,
  "frequency_source": "profile B",
  "full_scan_ns_total": 1280990,
  "generated_classifier_source_size_bytes": 2183,
  "generated_scanner_source_size_bytes": 29131,
  "granularity": "fine",
  "granularity_normalized": "fine",
  "input_bytes_total": 225019,
  "instructions": null,
  "layout_metadata": {
    "layout_policy": "class_blocks_sorted_by_profile_frequency",
    "profile_counts": {
      "ACC::DELIM::tok=LBRACE::aux=DELIM::prio0::rb0": 1,
      "ACC::DELIM::tok=RBRACE::aux=DELIM::prio0::rb0": 1,
      "ACC::DELIM::tok=SEMI::aux=DELIM::prio0::rb0": 5391,
      "ACC::IDENT::tok=IDENT::aux=WORD::prio0::rb1": 44628,
      "ACC::NUMBER::tok=INT::aux=NUMBER::prio0::rb1": 6067,
      "ACC::OPERATOR::tok=ASSIGN::aux=OP::prio0::rb1": 6294,
      "ACC::OPERATOR::tok=EQEQ::aux=OP::prio0::rb0": 451,
      "ACC::OPERATOR::tok=MINUS::aux=OP::prio0::rb0": 455,
      "ACC::OPERATOR::tok=PLUS::aux=OP::prio0::rb0": 417,
      "ACC::OPERATOR::tok=SLASH::aux=OP::prio0::rb0": 462,
      "ACC::OPERATOR::tok=STAR::aux=OP::prio0::rb0": 444,
      "ACC::WHITESPACE::tok=WS::aux=WS::prio0::rb0": 5393,
      "DEAD": 32320
    },
    "profile_source": "B"
  },
  "leaf_count": 17,
  "lexical_errors_total": 0,
  "max_intervals_per_class": 1,
  "mean_dispatch_depth_over_states": 8.941176470588236,
  "mean_input_bytes": 112509.5,
  "method_id": "B4",
  "method_label": "frequency-aware interval encoding",
  "num_accepting_states_nonrb": 12,
  "num_accepting_states_rb": 3,
  "num_accepting_states_total": 15,
  "num_inputs": 2,
  "num_intervals_total": 17,
  "num_semantic_classes": 17,
  "num_states": 17,
  "num_token_families_with_rb_split": 1,
  "opt_level": "-O3",
  "perf_available": false,
  "profile_condition": "same_B",
  "profile_input_bytes": 70004,
  "profile_scenario": "same_B",
  "profile_source": "B",
  "profile_trace_len": 102324,
  "rollback_metadata_available": true,
  "rollback_split_condition": "on",
  "rollbackacc_predicate_available": true,
  "rollbackacc_predicate_comparison_sites": 3,
  "rollbackacc_predicate_expected_depth": 1.8118525468120872,
  "rollbackacc_predicate_num_intervals": 2,
  "rollbackacc_predicate_worst_case_depth": 3,
  "seed": 0,
  "semantic_class_count_for_dispatch": 17,
  "semantic_class_count_under_layout": 17,
  "semantic_comparisons_total": 744058,
  "semantic_label_mode": "fine",
  "status": "completed",
  "throughput_bytes_per_sec": 175660231.53966853,
  "tokens_per_second_aggregate": 81097432.4545859,
  "transition_calls_total": 328902,
  "transition_instruction_count": 8,
  "transition_ns_per_call": 0.6648694913420452,
  "transition_trace_ns_total": 26461222,
  "worst_case_depth": 16,
  "worst_case_dispatch_depth": 16
}